LICENSE
MANIFEST.in
README.md
setup.cfg
setup.py
docs/_docs/getting-started/img/detail.png
docs/_docs/getting-started/img/github-workflow-artifact.png
docs/_docs/getting-started/img/github-workflow.png
docs/_docs/getting-started/img/gridtest.png
docs/_site/api/assets/file.png
docs/_site/api/assets/logo.gif
docs/_site/api/assets/logo.png
docs/_site/api/assets/minus.png
docs/_site/api/assets/plus.png
docs/_site/assets/img/apple-touch-icon.png
docs/_site/assets/img/logo_small.gif
docs/_site/assets/img/siteicon.png
docs/_site/assets/img/sprout-cute-1.gif
docs/_site/assets/img/touch-icon.png
docs/_site/assets/img/logo/blue.png
docs/_site/assets/img/logo/g-yellow.png
docs/_site/assets/img/logo/gridtest.gif
docs/_site/assets/img/logo/t-yellow.png
docs/_site/assets/img/logo/yellow.png
docs/_site/getting-started/img/detail.png
docs/_site/getting-started/img/gridtest.png
docs/api/assets/file.png
docs/api/assets/logo.gif
docs/api/assets/logo.png
docs/api/assets/minus.png
docs/api/assets/plus.png
docs/assets/img/apple-touch-icon.png
docs/assets/img/logo_small.gif
docs/assets/img/siteicon.png
docs/assets/img/sprout-cute-1.gif
docs/assets/img/touch-icon.png
docs/assets/img/logo/blue.png
docs/assets/img/logo/g-yellow.png
docs/assets/img/logo/gridtest.gif
docs/assets/img/logo/t-yellow.png
docs/assets/img/logo/yellow.png
gridtest/__init__.py
gridtest/decorators.py
gridtest/defaults.py
gridtest/func.py
gridtest/utils.py
gridtest/version.py
gridtest.egg-info/PKG-INFO
gridtest.egg-info/SOURCES.txt
gridtest.egg-info/dependency_links.txt
gridtest.egg-info/entry_points.txt
gridtest.egg-info/not-zip-safe
gridtest.egg-info/requires.txt
gridtest.egg-info/top_level.txt
gridtest/client/__init__.py
gridtest/client/check.py
gridtest/client/generate.py
gridtest/client/gridview.py
gridtest/client/shell.py
gridtest/client/test.py
gridtest/client/update.py
gridtest/logger/__init__.py
gridtest/logger/message.py
gridtest/logger/namer.py
gridtest/logger/progress.py
gridtest/logger/spinner.py
gridtest/main/__init__.py
gridtest/main/check.py
gridtest/main/expand.py
gridtest/main/generate.py
gridtest/main/grids.py
gridtest/main/helpers.py
gridtest/main/substitute.py
gridtest/main/test.py
gridtest/main/update.py
